ushmm/__init__.py
ushmm/testimonies.py
ushmm-0.0.6.dist-info/LICENSE
ushmm-0.0.6.dist-info/METADATA
ushmm-0.0.6.dist-info/WHEEL
ushmm-0.0.6.dist-info/top_level.txt
ushmm-0.0.6.dist-info/RECORD
