Metadata-Version: 2.1
Name: ushmm
Version: 0.0.6
Summary: A suite of tools for working with data at the United States Holocaust Memorial Museum
Home-page: https://github.com/wjbmattingly/ushmm
Author: W.J.B. Mattingly
Keywords: pdf image testimonies
Classifier: Topic :: Software Development :: Build Tools
Classifier: License :: OSI Approved :: MIT License
Classifier: Programming Language :: Python :: 3.10
Classifier: Operating System :: Microsoft :: Windows
Requires-Python: >=3.7
License-File: LICENSE
Requires-Dist: pdf2image
Requires-Dist: Pillow
Requires-Dist: pytesseract
Requires-Dist: unidecode
Requires-Dist: opencv-python
